Workbook

Sheet All 23 Ideas
A1: # | B1: Idea ID | C1: Filed on | D1: Filed by | E1: Title on card | F1: Board area | G1: Status | H1: Urgent | I1: The problem | J1: Proposed fix | K1: Expected impact | L1: Evidence - which data shows it | M1: Currently assigned to | N1: AI rank | O1: AI impact | P1: AI feasibility | Q1: AI strategic fit | R1: AI reason | S1: Group | T1: Distinct idea | U1: Card type | V1: Duplicate of (ID) | W1: Reassign to | X1: Owner to reassign to | Y1: Recommended action | Z1: Existing MyJKKN module | AA1: MyJKKN solution / suggestion | AB1: Review note (ready to paste)
A2: 1 | B2: c4ebb142 | C2: 2026-08-04 | D2: SAVITHA K | E2: Laboratory Improvement Initiative | F2: COE / Academic | G2: Under Review | H2: No | I2: The laboratory contains several expired chemicals and materials that should be removed and disposed of properly. Additionally, reorganizing the laboratory layout and improving the room arrangement would create a safer, cleaner, and more efficient working environment." | J2: Remove and properly dispose of all expired chemicals and materials according to safety guidelines. Reorganize the laboratory layout by arranging equipment and materials systematically, improving storage, and optimizing the available workspace for better safety and efficiency. | K2: Proper disposal of expired materials and reorganization of the laboratory will improve safety, cleanliness, space utilization, workflow efficiency, and compliance with laboratory standards. | L2: The observations and recommendations are based on laboratory analysis, site inspection, and information gathered during the assessment. | M2: VISWANATHAN S, BOOBALAN A | N2: 9 | O2: 4 | P2: 4 | Q2: 4 | R2: Disposing of expired chemicals is a safety and compliance matter and cheap to do. | S2: F | T2: Lab - dispose expired chemicals, reorganise lab | U2: Master | W2: Pharmacy | X2: Rajkumar J | Y2: Approve | Z2: Inventory (/ims) - expiry tracking | AA2: Physical disposal is a safety action for the Pharmacy principal. In MyJKKN: track chemical expiry in Inventory. 3 JKKN Pharmacy batches are already past expiry and still in stock. | AB2: Approved. Dispose of expired chemicals now; chemical expiry will be tracked in Inventory.
A3: 2 | B3: 04c4c414 | C3: 2026-08-04 | D3: SELVAMANI S | E3: JKKN COLLEGE OF PHARMACY | F3: COE / Academic | G3: Under Review | H3: No | I3: The laboratory contains several expired chemicals and materials that should be removed and disposed of properly. Additionally, reorganizing the laboratory layout and improving the room arrangement would create a safer, cleaner, and more efficient working environment." | J3: Remove and properly dispose of all expired chemicals and materials according to safety guidelines. Reorganize the laboratory layout by arranging equipment and materials systematically, improving storage, and optimizing the available workspace for better safety and efficiency. | K3: Proper disposal of expired materials and reorganization of the laboratory will improve safety, cleanliness, space utilization, workflow efficiency, and compliance with laboratory standards. | L3: The observations and recommendations are based on laboratory analysis, site inspection, and information gathered during the assessment. | M3: VISWANATHAN S, BOOBALAN A | N3: 10 | O3: 4 | P3: 4 | Q3: 4 | R3: Duplicate of the lab safety and disposal idea; same safety and compliance value. | S3: F | T3: Lab - dispose expired chemicals, reorganise lab | U3: Duplicate | V3: c4ebb142 | W3: Pharmacy | X3: Rajkumar J | Y3: Close as duplicate | Z3: Inventory (/ims) - expiry tracking | AA3: Physical disposal is a safety action for the Pharmacy principal. In MyJKKN: track chemical expiry in Inventory. 3 JKKN Pharmacy batches are already past expiry and still in stock. | AB3: Same proposal as c4ebb142, filed earlier. Closing this copy; you have been added as a contributor on the original.
A4: 3 | B4: 98a8204e | C4: 2026-08-06 | D4: MOURIESWARAN A | E4: Reduce Waiting Time for Certificate, Transcript, and Mark Sheet Processing | F4: COE / Academic | G4: Under Review | H4: No | I4: Students experience long waiting times to receive certificates, transcripts, and mark sheets due to manual processing, lack of status updates, and delays in approvals. This affects students applying for higher studies, placements, and jobs. | J4: Implement an online application and tracking system with defined processing timelines. Digitize records, automate approval workflows, and notify students through SMS/email at each stage of processing. | K4: Reduced waiting time and office visits.Improved student satisfaction | L4: Frequent student complaints regarding delays | M4: VISWANATHAN S, BOOBALAN A | N4: 14 | O4: 4 | P4: 4 | Q4: 4 | R4: Certificate tracking resolves frequent complaints; duplicate of the urgent version. | S4: A | T4: Certificate / transcript / mark sheet delays | U4: Master | W4: COE | X4: No COE owner on the board (coe role: Silambarasan V, COE Official, COE JKKNCAS / S. Umavathi) | Y4: Approve | Z4: Service Requests (/service-requests) | AA4: Already live: online request, approval workflow, timeline, Bonafide / Course Completion PDF. Gaps: (1) record fulfilment - only 4 of 988 marked fulfilled; (2) notify the learner on approved / ready / rejected; (3) turnaround target + overdue filter; (4) enable certificate PDFs on all live certificate types; (5) add COE service types for transcript, duplicate / consolidated mark sheet, provisional certificate. | AB4: Confirmed by MyJKKN data: 562 approved certificate requests were never marked fulfilled, 536 of them older than 7 days. Approved for fulfilment tracking, learner notifications, turnaround targets and new COE service types.
A5: 4 | B5: dd3afcf9 | C5: 2026-08-10 | D5: VAISHNAVI P | E5: Dental | F5: COE / Academic | G5: Under Review | H5: Yes | I5: Delay in patient history and records, heavy patient load ,space and infrastructure issues, poor department coordination, software problems, and shortage of required equipment. | J5: Improve digital coordination, standardized procedures, upgrade clinic facilities, service equipment and provide required machine and instruments | K5: Faster patient care,better coordination, improved student experience and better quality of treatment. | L5: Patient feedback, staff feedback, records, equipment issues, and clinical observation. | M5: VISWANATHAN S, BOOBALAN A | N5: 22 | O5: 4 | P5: 2 | Q5: 4 | R5: Dental issues are broad and costly to fix; feedback evidence and urgent flag. | S5: B | T5: Dental - records delay, patient load, space, equipment (broad) | U5: Master | W5: Dental Hospital | X5: Dhinesh Kumar C | Y5: Send back to split | Z5: None (no patient module) | AA5: Too broad to build. Ask the author to re-file as one card per problem with one number each. Appointment delays are covered by c913913b and medicine expiry by 3aad071d. | AB5: Too broad to act on. Please re-file as separate cards - one problem, one number each.
A6: 5 | B6: 992e5458 | C6: 2026-08-10 | D6: SHRIYA JULIET D | E6: Procurement | F6: COE / Academic | G6: Under Review | H6: No | I6: We observed that procurement involves multiple steps, such as identifying requirements, getting quotations, purchasing, receiving, and maintaining materials. Proper coordination is needed to avoid delays and shortages. | J6: We propose maintaining a systematic procurement record for requirements, quotations, suppliers, purchases, bills, and stock. Materials should be categorized and stored properly after receiving. | K6: This will help reduce procurement delays, prevent material shortages and wastage, and improve stock management. It will also make the purchasing process more organized and transparent. | L6: The improvement can be measured using purchase records, quotation details, stock registers, bills, procurement time, and quantity of materials received. Comparing these records will show the effectiveness of the procurement process | M6: VISWANATHAN S, BOOBALAN A | N6: 57 | O6: 3 | P6: 3 | Q6: 3 | R6: Systematic procurement records help, but the proposal is generic. | S6: J | T6: Procurement - digital purchase request, approvals, vendor list | U6: Weaker version | V6: 7793da9e | W6: Procurement | X6: Salini P | Y6: Merge into master | Z6: Procurement (/procurement) | AA6: Already live: 38 requests, 31 RFQs, 36 quotations, 15 purchase orders. Gaps: 0 goods receipts and 0 vendor ratings. Make GRN mandatory to close a PO, start vendor ratings, enforce 3 quotations above a set amount, use reorder levels. | AB6: Same proposal as 7793da9e, filed earlier. Closing this copy; you have been added as a contributor on the original.
A7: 6 | B7: 89570ea6 | C7: 2026-08-10 | D7: SRIKANTH K | E7: Dental | F7: COE / Academic | G7: Under Review | H7: No | I7: Delay in patient history and records, heavy patient load, space and infrastructure issues, poor department coordination, software problems, and shortage of required equipment. | J7: Improve digital coordination, standardize procedures, upgrade clinic facilities, service equipment, and provide required machines and instruments. | K7: Faster patient care, better coordination, improved student experience, and better quality of treatment. | L7: Patient feedback, staff feedback, records, equipment issues, and clinic observations. | M7: VISWANATHAN S, BOOBALAN A | N7: 45 | O7: 3 | P7: 2 | Q7: 4 | R7: Broad, costly dental improvements; evidence is generic. | S7: B | T7: Dental - records delay, patient load, space, equipment (broad) | U7: Duplicate | V7: dd3afcf9 | W7: Dental Hospital | X7: Dhinesh Kumar C | Y7: Close as duplicate | Z7: None (no patient module) | AA7: Too broad to build. Ask the author to re-file as one card per problem with one number each. Appointment delays are covered by c913913b and medicine expiry by 3aad071d. | AB7: Same proposal as dd3afcf9, filed earlier. Closing this copy; you have been added as a contributor on the original.
A8: 7 | B8: f255de95 | C8: 2026-08-18 | D8: SAVITHA K | E8: Impact of Improved Laboratory Infrastructure on Student Satisfaction and Institutional Growth | F8: COE / Academic | G8: Under Review | H8: No | I8: Lab room appearance, flooring, and fan facilities are not up to the expected standard. Due to these inadequate facilities, students may feel uncomfortable while using the laboratory, which can affect their learning experience and overall satisfaction. | J8: The laboratory can be improved by providing a clean and attractive ambience, proper flooring, adequate fans, good lighting, and better overall appearance. A comfortable and well-maintained laboratory will improve students’ satisfaction and create a positive impression of the college. Students may also share their positive experience with others, which can support the college’s reputation and admissions. In the long term, the institution can recover infrastructure-related investments through appropriate fee planning, subject to applicable regulations, while gaining benefits through improved student satisfaction, admissions, and institutional image. | K8: Improved laboratory infrastructure will provide students with a comfortable and attractive learning environment. This can increase student satisfaction, create positive word-of-mouth publicity, improve the college’s reputation, and attract more admissions, benefiting the institution’s overall growth. | L8: The laboratory was directly visited and the existing infrastructure and facilities were observed. Information regarding the room condition, flooring, fan facilities, and overall ambience was also collected through direct observation and interaction with the concerned staff. | M8: VISWANATHAN S, BOOBALAN A | N8: 59 | O8: 2 | P8: 3 | Q8: 3 | R8: Cosmetic lab upgrades; benefits are speculative and observation-based. | S8: G | T8: Lab - flooring, fans, lighting, ambience | U8: Master | W8: Pharmacy | X8: Rajkumar J | Y8: Hold for details | Z8: Resource Management (/resource-management) - maintenance | AA8: Facilities work, not software. Log as a maintenance job once the lab is named, photographed and costed. | AB8: Please name the lab and add photos and a cost estimate.
A9: 8 | B9: 3aad071d | C9: 2026-08-18 | D9: SHRIYA JULIET D | E9: Dental hospital | F9: COE / Academic | G9: Under Review | H9: Yes | I9: Medicine expiry dates and stock details may not always be updated regularly. This can lead to expired medicines, stock wastage, or difficulty in identifying available medicines. | J9: Maintain an updated medicine stock register with expiry dates and use a regular checking system. Near-expiry medicines can be identified and managed on time. | K9: This will reduce medicine wastage and improve stock accuracy. It will also ensure that only safe and valid medicines are available for patients. | L9: Stock register, expiry-date records, purchase records, and the number of expired or near-expiry medicines can be used as evidence. | M9: VISWANATHAN S, BOOBALAN A | N9: 21 | O9: 3 | P9: 5 | Q9: 4 | R9: Medicine expiry register is simple, low cost and improves patient safety. | S9: E | T9: Dental - medicine stock + expiry register | U9: Master | W9: Dental Hospital | X9: Dhinesh Kumar C | Y9: Approve | Z9: Inventory (/ims) - expiry tracking | AA9: Already built. Switch on expiry tracking for all dental medicine items, enter expiry at goods receipt, add a 30 / 60 / 90-day near-expiry alert. Today 0 of 56 Dental Student Store batches carry an expiry date. | AB9: Approved. Inventory already supports expiry dates; only 23 of 249 batches have one. Action: switch on expiry tracking for all dental medicine items and add a near-expiry alert.
A10: 9 | B10: a301440c | C10: 2026-08-18 | D10: SELVAMANI S | E10: Impact of Improved Laboratory Infrastructure on Student Satisfaction and Institutional Growth | F10: COE / Academic | G10: Under Review | H10: No | I10: Lab room appearance, flooring, and fan facilities are not up to the expected standard. Due to these inadequate facilities, students may feel uncomfortable while using the laboratory, which can affect their learning experience and overall satisfaction. | J10: The laboratory can be improved by providing a clean and attractive ambience, proper flooring, adequate fans, good lighting, and better overall appearance. A comfortable and well-maintained laboratory will improve students’ satisfaction and create a positive impression of the college. Students may also share their positive experience with others, which can support the college’s reputation and admissions. In the long term, the institution can recover infrastructure-related investments through appropriate fee planning, subject to applicable regulations, while gaining benefits through improved student satisfaction, admissions, and institutional image. | K10: Improved laboratory infrastructure will provide students with a comfortable and attractive learning environment. This can increase student satisfaction, create positive word-of-mouth publicity, improve the college’s reputation, and attract more admissions, benefiting the institution’s overall growth. | L10: The laboratory was directly visited and the existing infrastructure and facilities were observed. Information regarding the room condition, flooring, fan facilities, and overall ambience was also collected through direct observation and interaction with the concerned staff. | M10: VISWANATHAN S, BOOBALAN A | N10: 60 | O10: 2 | P10: 3 | Q10: 3 | R10: Duplicate lab ambience proposal with speculative benefits. | S10: G | T10: Lab - flooring, fans, lighting, ambience | U10: Duplicate | V10: f255de95 | W10: Pharmacy | X10: Rajkumar J | Y10: Close as duplicate | Z10: Resource Management (/resource-management) - maintenance | AA10: Facilities work, not software. Log as a maintenance job once the lab is named, photographed and costed. | AB10: Same proposal as f255de95, filed earlier. Closing this copy; you have been added as a contributor on the original.
A11: 10 | B11: 99f3eb6c | C11: 2026-08-19 | D11: SARANPRIYA R | E11: Pharmacy department | F11: COE / Academic | G11: Under Review | H11: No | I11: Lab visit was not permitted. Only purchasing details and museum-related information were provided. | J11: Improve the flooring and make necessary changes to the surrounding areas to create a cleaner, safer, and more comfortable environment. | K11: The laboratory facilities should be improved, and the latest/current chemical products required for practical work should be made available. | L11: Visit directly | M11: VISWANATHAN S, BOOBALAN A | N11: 67 | O11: 2 | P11: 3 | Q11: 2 | R11: Problem and fix are mismatched; flooring and chemicals are vaguely defined. | S11: H | T11: Pharmacy - "lab visit not permitted" + flooring | U11: Not pursued | W11: Pharmacy | X11: Rajkumar J | Y11: Not pursue | Z11: None | AA11: Problem and fix do not match. The real finding is that entry to the lab was refused - pass to the Pharmacy owner as a Gemba access issue. | AB11: The problem (lab visit refused) and the fix (flooring) do not match. The access refusal has been passed to the Pharmacy owner.
A12: 11 | B12: bd51d5b5 | C12: 2026-08-19 | D12: SARANYA P | E12: Pharmacy department | F12: COE / Academic | G12: Under Review | H12: No | I12: Lab visit was not permitted. Only purchasing details and museum-related information were provided. | J12: Improve the flooring and make necessary changes to the surrounding areas to create a cleaner, safer, and more comfortable environment. | K12: “The laboratory facilities should be improved, and the latest/current chemical products required for practical work should be made available.” | L12: Visit directly. | M12: VISWANATHAN S, BOOBALAN A | N12: 68 | O12: 2 | P12: 3 | Q12: 2 | R12: Duplicate pharmacy lab idea with unclear problem and weak evidence. | S12: H | T12: Pharmacy - "lab visit not permitted" + flooring | U12: Duplicate | V12: 99f3eb6c | W12: Pharmacy | X12: Rajkumar J | Y12: Close as duplicate | Z12: None | AA12: Problem and fix do not match. The real finding is that entry to the lab was refused - pass to the Pharmacy owner as a Gemba access issue. | AB12: Same proposal as 99f3eb6c, filed earlier. Closing this copy; you have been added as a contributor on the original.
A13: 12 | B13: c55831f9 | C13: 2026-09-02 | D13: MAHIBALAN M | E13: Automated Academic Document Issuance & Tracking System | F13: COE / Academic | G13: Under Review | H13: Yes | I13: Students experience long waiting times to receive certificates, transcripts, and mark sheets due to manual processing, lack of status updates, and delays in approvals. This affects students applying for higher studies, placements, and jobs. | J13: Implement an online application and tracking system with defined processing timelines. Digitize records, automate approval workflows, and notify students through SMS/email at each stage of processing. | K13: Reduced waiting time and office visits. Improved student satisfaction | L13: which data shows it Frequent student complaints regarding delays | M13: VISWANATHAN S, BOOBALAN A | N13: 3 | O13: 4 | P13: 4 | Q13: 5 | R13: Document issuance tracking fixes frequent complaints and affects placements and higher studies; urgent. | S13: A | T13: Certificate / transcript / mark sheet delays | U13: Duplicate | V13: 98a8204e | W13: COE | X13: No COE owner on the board (coe role: Silambarasan V, COE Official, COE JKKNCAS / S. Umavathi) | Y13: Close as duplicate | Z13: Service Requests (/service-requests) | AA13: Already live: online request, approval workflow, timeline, Bonafide / Course Completion PDF. Gaps: (1) record fulfilment - only 4 of 988 marked fulfilled; (2) notify the learner on approved / ready / rejected; (3) turnaround target + overdue filter; (4) enable certificate PDFs on all live certificate types; (5) add COE service types for transcript, duplicate / consolidated mark sheet, provisional certificate. | AB13: Same proposal as 98a8204e, filed earlier. Closing this copy; you have been added as a contributor on the original.
A14: 13 | B14: de8c082c | C14: 2026-09-02 | D14: KISHORE RAJ L | E14: COE / Academic | F14: COE / Academic | G14: Under Review | H14: No | I14: Students experience long waiting times to receive certificates, transcripts, and mark sheets due to manual processing, lack of status updates, and delays in approvals. This affects students applying for higher studies, placements, and jobs. | J14: Implement an online application and tracking system with defined processing timelines. Digitize records, automate approval workflows, and notify students through SMS/email at each stage of processing. | K14: Reduced waiting time and office visits.Improved student satisfaction | L14: Frequent student complaints regarding delay. | M14: VISWANATHAN S, BOOBALAN A | N14: 15 | O14: 4 | P14: 4 | Q14: 4 | R14: Same document-issuance tracking idea, backed by complaint evidence. | S14: A | T14: Certificate / transcript / mark sheet delays | U14: Duplicate | V14: 98a8204e | W14: COE | X14: No COE owner on the board (coe role: Silambarasan V, COE Official, COE JKKNCAS / S. Umavathi) | Y14: Close as duplicate | Z14: Service Requests (/service-requests) | AA14: Already live: online request, approval workflow, timeline, Bonafide / Course Completion PDF. Gaps: (1) record fulfilment - only 4 of 988 marked fulfilled; (2) notify the learner on approved / ready / rejected; (3) turnaround target + overdue filter; (4) enable certificate PDFs on all live certificate types; (5) add COE service types for transcript, duplicate / consolidated mark sheet, provisional certificate. | AB14: Same proposal as 98a8204e, filed earlier. Closing this copy; you have been added as a contributor on the original.
A15: 14 | B15: 79dbcdab | C15: 2026-09-02 | D15: KAVIYA V | E15: COE / Academic | F15: COE / Academic | G15: Under Review | H15: No | I15: Students experience long waiting times to receive certificates, transcripts, and mark sheets due to manual processing, lack of status updates, and delays in approvals. This affects students applying for higher studies, placements, and jobs. | J15: Implement an online application and tracking system with defined processing timelines. Digitize records, automate approval workflows, and notify students through SMS/email at each stage of processing. | K15: Reduced waiting time and office visits.Improved student satisfaction | L15: Frequent student complaints regarding delay. | M15: VISWANATHAN S, BOOBALAN A | N15: 16 | O15: 4 | P15: 4 | Q15: 4 | R15: Duplicate COE document tracking proposal with the same complaint evidence. | S15: A | T15: Certificate / transcript / mark sheet delays | U15: Duplicate | V15: 98a8204e | W15: COE | X15: No COE owner on the board (coe role: Silambarasan V, COE Official, COE JKKNCAS / S. Umavathi) | Y15: Close as duplicate | Z15: Service Requests (/service-requests) | AA15: Already live: online request, approval workflow, timeline, Bonafide / Course Completion PDF. Gaps: (1) record fulfilment - only 4 of 988 marked fulfilled; (2) notify the learner on approved / ready / rejected; (3) turnaround target + overdue filter; (4) enable certificate PDFs on all live certificate types; (5) add COE service types for transcript, duplicate / consolidated mark sheet, provisional certificate. | AB15: Same proposal as 98a8204e, filed earlier. Closing this copy; you have been added as a contributor on the original.
A16: 15 | B16: b5428ff8 | C16: 2026-09-02 | D16: SAVITHA K | E16: Dental College Crowd Management System | F16: COE / Academic | G16: Under Review | H16: No | I16: The dental college experiences heavy patient crowd, especially during peak hours. This leads to long queues, increased waiting time, congestion in the registration and treatment areas, and difficulty in managing patient flow. The lack of an organized queue or appointment system causes unnecessary crowding and delays in providing dental services. | J16: To control the rush in the dental college, a proper token and queue management system can be introduced. Patients can be given tokens or time-based appointments to avoid overcrowding. An online registration and appointment facility can also be provided, allowing patients to book their visits in advance. Separate areas for registration, consultation, billing, and treatment can be arranged to improve patient flow. This system will reduce waiting time, avoid unnecessary crowding, and make the dental services more organized and efficient. | K16: The proposed system is expected to reduce patient crowding and waiting time in the dental college. It will improve the smooth flow of patients and reduce confusion during registration, consultation, and treatment. Staff can manage patients more efficiently, which will reduce their workload. Overall, it will provide a better patient experience, faster service, improved operational efficiency, and a more organized dental college environment. | L16: Eye witnesses | M16: VISWANATHAN S, BOOBALAN A | N16: 34 | O16: 3 | P16: 4 | Q16: 3 | R16: Duplicate crowd management proposal; eyewitness evidence only. | S16: C | T16: Dental - token / queue system for patient crowd | U16: Master | W16: Dental Hospital | X16: Dhinesh Kumar C | Y16: Merge scope with c913913b | Z16: None (new build) | AA16: Run as one pilot with the appointment card c913913b: slots per chair, token for walk-ins. Build a module only if the pilot reduces waiting time. | AB16: Taken up as part of the dental appointment pilot (c913913b).
A17: 16 | B17: 2b02c1b6 | C17: 2026-09-03 | D17: SELVAMANI S | E17: Dental College Crowd Management System | F17: COE / Academic | G17: Under Review | H17: No | I17: The dental college experiences heavy patient crowd, especially during peak hours. This leads to long queues, increased waiting time, congestion in the registration and treatment areas, and difficulty in managing patient flow. The lack of an organized queue or appointment system causes unnecessary crowding and delays in providing dental services. | J17: To control the rush in the dental college, a proper token and queue management system can be introduced. Patients can be given tokens or time-based appointments to avoid overcrowding. An online registration and appointment facility can also be provided, allowing patients to book their visits in advance. Separate areas for registration, consultation, billing, and treatment can be arranged to improve patient flow. This system will reduce waiting time, avoid unnecessary crowding, and make the dental services more organized and efficient. | K17: The proposed system is expected to reduce patient crowding and waiting time in the dental college. It will improve the smooth flow of patients and reduce confusion during registration, consultation, and treatment. Staff can manage patients more efficiently, which will reduce their workload. Overall, it will provide a better patient experience, faster service, improved operational efficiency, and a more organized dental college environment. | L17: Eye witnesses | M17: VISWANATHAN S, BOOBALAN A | N17: 33 | O17: 3 | P17: 4 | Q17: 3 | R17: Token and queue system eases patient crowding; evidence is anecdotal. | S17: C | T17: Dental - token / queue system for patient crowd | U17: Duplicate | V17: b5428ff8 | W17: Dental Hospital | X17: Dhinesh Kumar C | Y17: Close as duplicate | Z17: None (new build) | AA17: Run as one pilot with the appointment card c913913b: slots per chair, token for walk-ins. Build a module only if the pilot reduces waiting time. | AB17: Same proposal as b5428ff8, filed earlier. Closing this copy; you have been added as a contributor on the original.
A18: 17 | B18: 84cdd57b | C18: 2026-10-06 | D18: ABHISHEK RAJ G | E18: Academic | F18: COE / Academic | G18: Under Review | H18: No | I18: Students experience long waiting times to receive certificates, transcripts, and mark sheets due to manual processing, lack of status updates, and delays in approvals. This affects students applying for higher studies, placements, and jobs. | J18: Implement an online application and tracking system with defined processing timelines. Digitize records, automate approval workflows, and notify students through SMS/email at each stage of processing. | K18: Reduced waiting time and office visits.Improved student satisfaction. | L18: Frequent student complaints regarding delay. | M18: VISWANATHAN S, BOOBALAN A | N18: 17 | O18: 4 | P18: 4 | Q18: 4 | R18: Duplicate document-issuance tracking proposal; same benefits. | S18: A | T18: Certificate / transcript / mark sheet delays | U18: Duplicate | V18: 98a8204e | W18: COE | X18: No COE owner on the board (coe role: Silambarasan V, COE Official, COE JKKNCAS / S. Umavathi) | Y18: Close as duplicate | Z18: Service Requests (/service-requests) | AA18: Already live: online request, approval workflow, timeline, Bonafide / Course Completion PDF. Gaps: (1) record fulfilment - only 4 of 988 marked fulfilled; (2) notify the learner on approved / ready / rejected; (3) turnaround target + overdue filter; (4) enable certificate PDFs on all live certificate types; (5) add COE service types for transcript, duplicate / consolidated mark sheet, provisional certificate. | AB18: Same proposal as 98a8204e, filed earlier. Closing this copy; you have been added as a contributor on the original.
A19: 18 | B19: 9c1e4cb3 | C19: 2026-10-06 | D19: KISHORE RAJ L | E19: Dental | F19: COE / Academic | G19: Under Review | H19: Yes | I19: Delay in patient history and records, heavy patient load ,space and infrastructure issues, poor department coordination, software problems, and shortage of required equipment. | J19: Improve digital coordination, standardized procedures, upgrade clinic facilities, service equipment and provide required machine and instruments | K19: Faster patient care,better coordination, improved student experience and better quality of treatment. | M19: VISWANATHAN S, BOOBALAN A | N19: 44 | O19: 3 | P19: 2 | Q19: 4 | R19: Broad dental fix without evidence; urgent flag only. | S19: B | T19: Dental - records delay, patient load, space, equipment (broad) | U19: Duplicate | V19: dd3afcf9 | W19: Dental Hospital | X19: Dhinesh Kumar C | Y19: Close as duplicate | Z19: None (no patient module) | AA19: Too broad to build. Ask the author to re-file as one card per problem with one number each. Appointment delays are covered by c913913b and medicine expiry by 3aad071d. | AB19: Same proposal as dd3afcf9, filed earlier. Closing this copy; you have been added as a contributor on the original.
A20: 19 | B20: 2db88fe5 | C20: 2026-10-06 | D20: RUBAN R | E20: Barcode scanning at dispensing to cut prescription errors and wait time | F20: COE / Academic | G20: Under Review | H20: Yes | I20: Medicines are picked and verified by hand, which is slow and leads to wrong-drug or wrong-strength mix-ups. Patients wait 25-30 minutes at the counter, and pharmacists spend much of their time on re-checking instead of counselling. | J20: Label every shelf bin and medicine pack with a barcode. Scan the prescription, then scan each medicine at picking and again at the final check. The system flags any mismatch before the medicine is handed over. Add a separate express queue for refills. | K20: Fewer dispensing errors, waiting time cut to about 10-15 minutes, less rework, and more pharmacist time for patient counselling. | L20: Log of dispensing errors and near-misses for the last 3 months (number), average waiting time from a one-week sample (minutes), and patient complaints or feedback about delays. | M20: VISWANATHAN S, BOOBALAN A | N20: 18 | O20: 4 | P20: 3 | Q20: 4 | R20: Barcode dispensing reduces medication errors and waits; patient safety, but needs hardware and system setup. | S20: I | T20: Pharmacy - barcode scan at dispensing | U20: Master | W20: Pharmacy | X20: Rajkumar J | Y20: Approve as pilot | Z20: Inventory (/ims) - sales / POS (no barcode field yet) | AA20: Enhancement to the Inventory sales screen plus labels and scanners. Collect the baseline first: 3 months of dispensing errors and a one-week waiting-time sample. | AB20: Approved as a pilot. Please attach the baseline first: 3 months of dispensing errors and a one-week waiting-time sample.
A21: 20 | B21: fef3462a | C21: 2026-10-06 | D21: KAVIYA V | E21: Dental | F21: COE / Academic | G21: Under Review | H21: No | I21: Delay in patient history and records, heavy patient load ,space and infrastructure issues, poor department coordination, software problems, and shortage of required equipment. | J21: Improve digital coordination, standardized procedures, upgrade clinic facilities, service equipment and provide required machine and instruments | K21: Faster patient care,better coordination, improved student experience and better quality of treatment. | M21: VISWANATHAN S, BOOBALAN A | N21: 66 | O21: 3 | P21: 2 | Q21: 3 | R21: Broad dental fix with no evidence and not urgent. | S21: B | T21: Dental - records delay, patient load, space, equipment (broad) | U21: Duplicate | V21: dd3afcf9 | W21: Dental Hospital | X21: Dhinesh Kumar C | Y21: Close as duplicate | Z21: None (no patient module) | AA21: Too broad to build. Ask the author to re-file as one card per problem with one number each. Appointment delays are covered by c913913b and medicine expiry by 3aad071d. | AB21: Same proposal as dd3afcf9, filed earlier. Closing this copy; you have been added as a contributor on the original.
A22: 21 | B22: 133d6b0c | C22: 2026-10-06 | D22: KISHORE RAJ L | E22: Pharmacy | F22: COE / Academic | G22: Under Review | H22: No | I22: Only purchasing details and museum-related information were provided. | J22: Improve the flooring and make necessary changes to the surrounding areas to create a cleaner, safer, and more comfortable environment. | L22: The laboratory facilities should be improved, and the latest/current chemical products required for practical work should be made available.” | M22: VISWANATHAN S, BOOBALAN A | N22: 69 | O22: 1 | P22: 3 | Q22: 2 | R22: Incoherent case: no stated impact and the problem does not match the fix. | S22: H | T22: Pharmacy - "lab visit not permitted" + flooring | U22: Duplicate | V22: 99f3eb6c | W22: Pharmacy | X22: Rajkumar J | Y22: Close as duplicate | Z22: None | AA22: Problem and fix do not match. The real finding is that entry to the lab was refused - pass to the Pharmacy owner as a Gemba access issue. | AB22: Same proposal as 99f3eb6c, filed earlier. Closing this copy; you have been added as a contributor on the original.
A23: 22 | B23: 7793da9e | C23: 2026-10-06 | D23: RUBAN R | E23: Digital purchase request and approval system with preferred vendor list | F23: COE / Academic | G23: Under Review | H23: Yes | I23: Purchase requests move on paper or WhatsApp and wait days for approval. Urgent items get bought at higher prices, quotes aren't compared consistently, and nobody can easily see what was ordered, from whom, or what is still pending. This delays work in every department. | J23: Move requests to one shared digital form with auto-routing to the approver. Keep a preferred vendor list with agreed rates, and require at least 3 quotes above a set amount. Add a simple tracker showing each request's status (requested, approved, ordered, received), and set reorder levels for regularly used items so they are bought in bulk. | K23: Approval time cut from about 5 days to 1-2 days, 8-10% savings from rate contracts and bulk buying, fewer urgent purchases, and a clear audit trail. | L23: Average days from request to order (sample of the last 20 requests), price differences paid for the same item across months, number of urgent or emergency purchases last quarter, and complaints about late supplies. | M23: VISWANATHAN S, BOOBALAN A | N23: 28 | O23: 4 | P23: 3 | Q23: 3 | R23: Digital purchasing saves cost and time across departments; needs change management. | S23: J | T23: Procurement - digital purchase request, approvals, vendor list | U23: Master | W23: Procurement | X23: Salini P | Y23: Approve | Z23: Procurement (/procurement) | AA23: Already live: 38 requests, 31 RFQs, 36 quotations, 15 purchase orders. Gaps: 0 goods receipts and 0 vendor ratings. Make GRN mandatory to close a PO, start vendor ratings, enforce 3 quotations above a set amount, use reorder levels. | AB23: Most of this is live in the Procurement module (38 requests, 31 RFQs, 15 purchase orders). Approved for the missing parts: goods-receipt entry, vendor ratings and the 3-quote rule.
A24: 23 | B24: c913913b | C24: 2026-10-06 | D24: RUBAN R | E24: Title: Appointment reminders and treatment follow-up tracking to cut no-shows and chair idle time Area: Patient Experience / Scheduling (or Operations) Target d | F24: COE / Academic | G24: Under Review | H24: Yes | I24: Appointments are booked in a register or by phone, with no reminders. Many patients miss visits, leaving chairs empty, while walk-ins crowd the waiting area. Patients in multi-visit treatments (root canal, braces, implants) often drop off midway, which hurts outcomes and revenue. | J24: Use one shared digital appointment sheet or booking tool with time slots for each chair and doctor. Send automatic WhatsApp or SMS reminders 1 day and 2 hours before the visit. Keep a follow-up tracker for every multi-visit treatment, with a call to patients who miss their next step within 3 days. Reserve a few daily slots for emergencies and walk-ins. | K24: No-shows cut from about 25% to 10%, waiting time reduced to 10-15 minutes, better chair utilisation, more patients completing treatment, and a smoother front desk. | L24: Number of no-shows and cancellations last month (from the register), average waiting time from a one-week sample (minutes), count of patients who left treatment incomplete last quarter, and patient complaints about delays. | M24: VISWANATHAN S, BOOBALAN A | N24: 19 | O24: 4 | P24: 4 | Q24: 4 | R24: Reminders and follow-up tracking cut no-shows cheaply; measurable and urgent. | S24: D | T24: Dental - appointment reminders + follow-up tracking | U24: Master | W24: Dental Hospital | X24: Dhinesh Kumar C | Y24: Approve as pilot | Z24: WhatsApp integration (reminders only); no appointment module | AA24: Four-week pilot in one department: shared appointment sheet, reminders through the existing MyJKKN WhatsApp integration. Measure no-shows and waiting time before and after. | AB24: Approved as a four-week pilot in one department. Record no-shows and waiting time before and after.

Sheet By Filed By
A1: Filed by | B1: Cards filed | C1: Masters (original ideas) | D1: Duplicates / weaker copies | E1: Not pursued | F1: Urgent cards | G1: COE | H1: Dental Hospital | I1: Pharmacy | J1: Procurement | K1: Idea IDs
A2: ABHISHEK RAJ G | B2: =COUNTIF('All 23 Ideas'!$D$2:$D$24,$A2) | C2: =COUNTIFS('All 23 Ideas'!$D$2:$D$24,$A2,'All 23 Ideas'!$U$2:$U$24,"Master") | D2: =COUNTIFS('All 23 Ideas'!$D$2:$D$24,$A2,'All 23 Ideas'!$U$2:$U$24,"Duplicate")+COUNTIFS('All 23 Ideas'!$D$2:$D$24,$A2,'All 23 Ideas'!$U$2:$U$24,"Weaker version") | E2: =COUNTIFS('All 23 Ideas'!$D$2:$D$24,$A2,'All 23 Ideas'!$U$2:$U$24,"Not pursued") | F2: =COUNTIFS('All 23 Ideas'!$D$2:$D$24,$A2,'All 23 Ideas'!$H$2:$H$24,"Yes") | G2: =COUNTIFS('All 23 Ideas'!$D$2:$D$24,$A2,'All 23 Ideas'!$W$2:$W$24,"COE") | H2: =COUNTIFS('All 23 Ideas'!$D$2:$D$24,$A2,'All 23 Ideas'!$W$2:$W$24,"Dental Hospital") | I2: =COUNTIFS('All 23 Ideas'!$D$2:$D$24,$A2,'All 23 Ideas'!$W$2:$W$24,"Pharmacy") | J2: =COUNTIFS('All 23 Ideas'!$D$2:$D$24,$A2,'All 23 Ideas'!$W$2:$W$24,"Procurement") | K2: 84cdd57b
A3: KAVIYA V | B3: =COUNTIF('All 23 Ideas'!$D$2:$D$24,$A3) | C3: =COUNTIFS('All 23 Ideas'!$D$2:$D$24,$A3,'All 23 Ideas'!$U$2:$U$24,"Master") | D3: =COUNTIFS('All 23 Ideas'!$D$2:$D$24,$A3,'All 23 Ideas'!$U$2:$U$24,"Duplicate")+COUNTIFS('All 23 Ideas'!$D$2:$D$24,$A3,'All 23 Ideas'!$U$2:$U$24,"Weaker version") | E3: =COUNTIFS('All 23 Ideas'!$D$2:$D$24,$A3,'All 23 Ideas'!$U$2:$U$24,"Not pursued") | F3: =COUNTIFS('All 23 Ideas'!$D$2:$D$24,$A3,'All 23 Ideas'!$H$2:$H$24,"Yes") | G3: =COUNTIFS('All 23 Ideas'!$D$2:$D$24,$A3,'All 23 Ideas'!$W$2:$W$24,"COE") | H3: =COUNTIFS('All 23 Ideas'!$D$2:$D$24,$A3,'All 23 Ideas'!$W$2:$W$24,"Dental Hospital") | I3: =COUNTIFS('All 23 Ideas'!$D$2:$D$24,$A3,'All 23 Ideas'!$W$2:$W$24,"Pharmacy") | J3: =COUNTIFS('All 23 Ideas'!$D$2:$D$24,$A3,'All 23 Ideas'!$W$2:$W$24,"Procurement") | K3: 79dbcdab, fef3462a
A4: KISHORE RAJ L | B4: =COUNTIF('All 23 Ideas'!$D$2:$D$24,$A4) | C4: =COUNTIFS('All 23 Ideas'!$D$2:$D$24,$A4,'All 23 Ideas'!$U$2:$U$24,"Master") | D4: =COUNTIFS('All 23 Ideas'!$D$2:$D$24,$A4,'All 23 Ideas'!$U$2:$U$24,"Duplicate")+COUNTIFS('All 23 Ideas'!$D$2:$D$24,$A4,'All 23 Ideas'!$U$2:$U$24,"Weaker version") | E4: =COUNTIFS('All 23 Ideas'!$D$2:$D$24,$A4,'All 23 Ideas'!$U$2:$U$24,"Not pursued") | F4: =COUNTIFS('All 23 Ideas'!$D$2:$D$24,$A4,'All 23 Ideas'!$H$2:$H$24,"Yes") | G4: =COUNTIFS('All 23 Ideas'!$D$2:$D$24,$A4,'All 23 Ideas'!$W$2:$W$24,"COE") | H4: =COUNTIFS('All 23 Ideas'!$D$2:$D$24,$A4,'All 23 Ideas'!$W$2:$W$24,"Dental Hospital") | I4: =COUNTIFS('All 23 Ideas'!$D$2:$D$24,$A4,'All 23 Ideas'!$W$2:$W$24,"Pharmacy") | J4: =COUNTIFS('All 23 Ideas'!$D$2:$D$24,$A4,'All 23 Ideas'!$W$2:$W$24,"Procurement") | K4: de8c082c, 9c1e4cb3, 133d6b0c
A5: MAHIBALAN M | B5: =COUNTIF('All 23 Ideas'!$D$2:$D$24,$A5) | C5: =COUNTIFS('All 23 Ideas'!$D$2:$D$24,$A5,'All 23 Ideas'!$U$2:$U$24,"Master") | D5: =COUNTIFS('All 23 Ideas'!$D$2:$D$24,$A5,'All 23 Ideas'!$U$2:$U$24,"Duplicate")+COUNTIFS('All 23 Ideas'!$D$2:$D$24,$A5,'All 23 Ideas'!$U$2:$U$24,"Weaker version") | E5: =COUNTIFS('All 23 Ideas'!$D$2:$D$24,$A5,'All 23 Ideas'!$U$2:$U$24,"Not pursued") | F5: =COUNTIFS('All 23 Ideas'!$D$2:$D$24,$A5,'All 23 Ideas'!$H$2:$H$24,"Yes") | G5: =COUNTIFS('All 23 Ideas'!$D$2:$D$24,$A5,'All 23 Ideas'!$W$2:$W$24,"COE") | H5: =COUNTIFS('All 23 Ideas'!$D$2:$D$24,$A5,'All 23 Ideas'!$W$2:$W$24,"Dental Hospital") | I5: =COUNTIFS('All 23 Ideas'!$D$2:$D$24,$A5,'All 23 Ideas'!$W$2:$W$24,"Pharmacy") | J5: =COUNTIFS('All 23 Ideas'!$D$2:$D$24,$A5,'All 23 Ideas'!$W$2:$W$24,"Procurement") | K5: c55831f9
A6: MOURIESWARAN A | B6: =COUNTIF('All 23 Ideas'!$D$2:$D$24,$A6) | C6: =COUNTIFS('All 23 Ideas'!$D$2:$D$24,$A6,'All 23 Ideas'!$U$2:$U$24,"Master") | D6: =COUNTIFS('All 23 Ideas'!$D$2:$D$24,$A6,'All 23 Ideas'!$U$2:$U$24,"Duplicate")+COUNTIFS('All 23 Ideas'!$D$2:$D$24,$A6,'All 23 Ideas'!$U$2:$U$24,"Weaker version") | E6: =COUNTIFS('All 23 Ideas'!$D$2:$D$24,$A6,'All 23 Ideas'!$U$2:$U$24,"Not pursued") | F6: =COUNTIFS('All 23 Ideas'!$D$2:$D$24,$A6,'All 23 Ideas'!$H$2:$H$24,"Yes") | G6: =COUNTIFS('All 23 Ideas'!$D$2:$D$24,$A6,'All 23 Ideas'!$W$2:$W$24,"COE") | H6: =COUNTIFS('All 23 Ideas'!$D$2:$D$24,$A6,'All 23 Ideas'!$W$2:$W$24,"Dental Hospital") | I6: =COUNTIFS('All 23 Ideas'!$D$2:$D$24,$A6,'All 23 Ideas'!$W$2:$W$24,"Pharmacy") | J6: =COUNTIFS('All 23 Ideas'!$D$2:$D$24,$A6,'All 23 Ideas'!$W$2:$W$24,"Procurement") | K6: 98a8204e
A7: RUBAN R | B7: =COUNTIF('All 23 Ideas'!$D$2:$D$24,$A7) | C7: =COUNTIFS('All 23 Ideas'!$D$2:$D$24,$A7,'All 23 Ideas'!$U$2:$U$24,"Master") | D7: =COUNTIFS('All 23 Ideas'!$D$2:$D$24,$A7,'All 23 Ideas'!$U$2:$U$24,"Duplicate")+COUNTIFS('All 23 Ideas'!$D$2:$D$24,$A7,'All 23 Ideas'!$U$2:$U$24,"Weaker version") | E7: =COUNTIFS('All 23 Ideas'!$D$2:$D$24,$A7,'All 23 Ideas'!$U$2:$U$24,"Not pursued") | F7: =COUNTIFS('All 23 Ideas'!$D$2:$D$24,$A7,'All 23 Ideas'!$H$2:$H$24,"Yes") | G7: =COUNTIFS('All 23 Ideas'!$D$2:$D$24,$A7,'All 23 Ideas'!$W$2:$W$24,"COE") | H7: =COUNTIFS('All 23 Ideas'!$D$2:$D$24,$A7,'All 23 Ideas'!$W$2:$W$24,"Dental Hospital") | I7: =COUNTIFS('All 23 Ideas'!$D$2:$D$24,$A7,'All 23 Ideas'!$W$2:$W$24,"Pharmacy") | J7: =COUNTIFS('All 23 Ideas'!$D$2:$D$24,$A7,'All 23 Ideas'!$W$2:$W$24,"Procurement") | K7: 2db88fe5, 7793da9e, c913913b
A8: SARANPRIYA R | B8: =COUNTIF('All 23 Ideas'!$D$2:$D$24,$A8) | C8: =COUNTIFS('All 23 Ideas'!$D$2:$D$24,$A8,'All 23 Ideas'!$U$2:$U$24,"Master") | D8: =COUNTIFS('All 23 Ideas'!$D$2:$D$24,$A8,'All 23 Ideas'!$U$2:$U$24,"Duplicate")+COUNTIFS('All 23 Ideas'!$D$2:$D$24,$A8,'All 23 Ideas'!$U$2:$U$24,"Weaker version") | E8: =COUNTIFS('All 23 Ideas'!$D$2:$D$24,$A8,'All 23 Ideas'!$U$2:$U$24,"Not pursued") | F8: =COUNTIFS('All 23 Ideas'!$D$2:$D$24,$A8,'All 23 Ideas'!$H$2:$H$24,"Yes") | G8: =COUNTIFS('All 23 Ideas'!$D$2:$D$24,$A8,'All 23 Ideas'!$W$2:$W$24,"COE") | H8: =COUNTIFS('All 23 Ideas'!$D$2:$D$24,$A8,'All 23 Ideas'!$W$2:$W$24,"Dental Hospital") | I8: =COUNTIFS('All 23 Ideas'!$D$2:$D$24,$A8,'All 23 Ideas'!$W$2:$W$24,"Pharmacy") | J8: =COUNTIFS('All 23 Ideas'!$D$2:$D$24,$A8,'All 23 Ideas'!$W$2:$W$24,"Procurement") | K8: 99f3eb6c
A9: SARANYA P | B9: =COUNTIF('All 23 Ideas'!$D$2:$D$24,$A9) | C9: =COUNTIFS('All 23 Ideas'!$D$2:$D$24,$A9,'All 23 Ideas'!$U$2:$U$24,"Master") | D9: =COUNTIFS('All 23 Ideas'!$D$2:$D$24,$A9,'All 23 Ideas'!$U$2:$U$24,"Duplicate")+COUNTIFS('All 23 Ideas'!$D$2:$D$24,$A9,'All 23 Ideas'!$U$2:$U$24,"Weaker version") | E9: =COUNTIFS('All 23 Ideas'!$D$2:$D$24,$A9,'All 23 Ideas'!$U$2:$U$24,"Not pursued") | F9: =COUNTIFS('All 23 Ideas'!$D$2:$D$24,$A9,'All 23 Ideas'!$H$2:$H$24,"Yes") | G9: =COUNTIFS('All 23 Ideas'!$D$2:$D$24,$A9,'All 23 Ideas'!$W$2:$W$24,"COE") | H9: =COUNTIFS('All 23 Ideas'!$D$2:$D$24,$A9,'All 23 Ideas'!$W$2:$W$24,"Dental Hospital") | I9: =COUNTIFS('All 23 Ideas'!$D$2:$D$24,$A9,'All 23 Ideas'!$W$2:$W$24,"Pharmacy") | J9: =COUNTIFS('All 23 Ideas'!$D$2:$D$24,$A9,'All 23 Ideas'!$W$2:$W$24,"Procurement") | K9: bd51d5b5
A10: SAVITHA K | B10: =COUNTIF('All 23 Ideas'!$D$2:$D$24,$A10) | C10: =COUNTIFS('All 23 Ideas'!$D$2:$D$24,$A10,'All 23 Ideas'!$U$2:$U$24,"Master") | D10: =COUNTIFS('All 23 Ideas'!$D$2:$D$24,$A10,'All 23 Ideas'!$U$2:$U$24,"Duplicate")+COUNTIFS('All 23 Ideas'!$D$2:$D$24,$A10,'All 23 Ideas'!$U$2:$U$24,"Weaker version") | E10: =COUNTIFS('All 23 Ideas'!$D$2:$D$24,$A10,'All 23 Ideas'!$U$2:$U$24,"Not pursued") | F10: =COUNTIFS('All 23 Ideas'!$D$2:$D$24,$A10,'All 23 Ideas'!$H$2:$H$24,"Yes") | G10: =COUNTIFS('All 23 Ideas'!$D$2:$D$24,$A10,'All 23 Ideas'!$W$2:$W$24,"COE") | H10: =COUNTIFS('All 23 Ideas'!$D$2:$D$24,$A10,'All 23 Ideas'!$W$2:$W$24,"Dental Hospital") | I10: =COUNTIFS('All 23 Ideas'!$D$2:$D$24,$A10,'All 23 Ideas'!$W$2:$W$24,"Pharmacy") | J10: =COUNTIFS('All 23 Ideas'!$D$2:$D$24,$A10,'All 23 Ideas'!$W$2:$W$24,"Procurement") | K10: c4ebb142, f255de95, b5428ff8
A11: SELVAMANI S | B11: =COUNTIF('All 23 Ideas'!$D$2:$D$24,$A11) | C11: =COUNTIFS('All 23 Ideas'!$D$2:$D$24,$A11,'All 23 Ideas'!$U$2:$U$24,"Master") | D11: =COUNTIFS('All 23 Ideas'!$D$2:$D$24,$A11,'All 23 Ideas'!$U$2:$U$24,"Duplicate")+COUNTIFS('All 23 Ideas'!$D$2:$D$24,$A11,'All 23 Ideas'!$U$2:$U$24,"Weaker version") | E11: =COUNTIFS('All 23 Ideas'!$D$2:$D$24,$A11,'All 23 Ideas'!$U$2:$U$24,"Not pursued") | F11: =COUNTIFS('All 23 Ideas'!$D$2:$D$24,$A11,'All 23 Ideas'!$H$2:$H$24,"Yes") | G11: =COUNTIFS('All 23 Ideas'!$D$2:$D$24,$A11,'All 23 Ideas'!$W$2:$W$24,"COE") | H11: =COUNTIFS('All 23 Ideas'!$D$2:$D$24,$A11,'All 23 Ideas'!$W$2:$W$24,"Dental Hospital") | I11: =COUNTIFS('All 23 Ideas'!$D$2:$D$24,$A11,'All 23 Ideas'!$W$2:$W$24,"Pharmacy") | J11: =COUNTIFS('All 23 Ideas'!$D$2:$D$24,$A11,'All 23 Ideas'!$W$2:$W$24,"Procurement") | K11: 04c4c414, a301440c, 2b02c1b6
A12: SHRIYA JULIET D | B12: =COUNTIF('All 23 Ideas'!$D$2:$D$24,$A12) | C12: =COUNTIFS('All 23 Ideas'!$D$2:$D$24,$A12,'All 23 Ideas'!$U$2:$U$24,"Master") | D12: =COUNTIFS('All 23 Ideas'!$D$2:$D$24,$A12,'All 23 Ideas'!$U$2:$U$24,"Duplicate")+COUNTIFS('All 23 Ideas'!$D$2:$D$24,$A12,'All 23 Ideas'!$U$2:$U$24,"Weaker version") | E12: =COUNTIFS('All 23 Ideas'!$D$2:$D$24,$A12,'All 23 Ideas'!$U$2:$U$24,"Not pursued") | F12: =COUNTIFS('All 23 Ideas'!$D$2:$D$24,$A12,'All 23 Ideas'!$H$2:$H$24,"Yes") | G12: =COUNTIFS('All 23 Ideas'!$D$2:$D$24,$A12,'All 23 Ideas'!$W$2:$W$24,"COE") | H12: =COUNTIFS('All 23 Ideas'!$D$2:$D$24,$A12,'All 23 Ideas'!$W$2:$W$24,"Dental Hospital") | I12: =COUNTIFS('All 23 Ideas'!$D$2:$D$24,$A12,'All 23 Ideas'!$W$2:$W$24,"Pharmacy") | J12: =COUNTIFS('All 23 Ideas'!$D$2:$D$24,$A12,'All 23 Ideas'!$W$2:$W$24,"Procurement") | K12: 992e5458, 3aad071d
A13: SRIKANTH K | B13: =COUNTIF('All 23 Ideas'!$D$2:$D$24,$A13) | C13: =COUNTIFS('All 23 Ideas'!$D$2:$D$24,$A13,'All 23 Ideas'!$U$2:$U$24,"Master") | D13: =COUNTIFS('All 23 Ideas'!$D$2:$D$24,$A13,'All 23 Ideas'!$U$2:$U$24,"Duplicate")+COUNTIFS('All 23 Ideas'!$D$2:$D$24,$A13,'All 23 Ideas'!$U$2:$U$24,"Weaker version") | E13: =COUNTIFS('All 23 Ideas'!$D$2:$D$24,$A13,'All 23 Ideas'!$U$2:$U$24,"Not pursued") | F13: =COUNTIFS('All 23 Ideas'!$D$2:$D$24,$A13,'All 23 Ideas'!$H$2:$H$24,"Yes") | G13: =COUNTIFS('All 23 Ideas'!$D$2:$D$24,$A13,'All 23 Ideas'!$W$2:$W$24,"COE") | H13: =COUNTIFS('All 23 Ideas'!$D$2:$D$24,$A13,'All 23 Ideas'!$W$2:$W$24,"Dental Hospital") | I13: =COUNTIFS('All 23 Ideas'!$D$2:$D$24,$A13,'All 23 Ideas'!$W$2:$W$24,"Pharmacy") | J13: =COUNTIFS('All 23 Ideas'!$D$2:$D$24,$A13,'All 23 Ideas'!$W$2:$W$24,"Procurement") | K13: 89570ea6
A14: VAISHNAVI P | B14: =COUNTIF('All 23 Ideas'!$D$2:$D$24,$A14) | C14: =COUNTIFS('All 23 Ideas'!$D$2:$D$24,$A14,'All 23 Ideas'!$U$2:$U$24,"Master") | D14: =COUNTIFS('All 23 Ideas'!$D$2:$D$24,$A14,'All 23 Ideas'!$U$2:$U$24,"Duplicate")+COUNTIFS('All 23 Ideas'!$D$2:$D$24,$A14,'All 23 Ideas'!$U$2:$U$24,"Weaker version") | E14: =COUNTIFS('All 23 Ideas'!$D$2:$D$24,$A14,'All 23 Ideas'!$U$2:$U$24,"Not pursued") | F14: =COUNTIFS('All 23 Ideas'!$D$2:$D$24,$A14,'All 23 Ideas'!$H$2:$H$24,"Yes") | G14: =COUNTIFS('All 23 Ideas'!$D$2:$D$24,$A14,'All 23 Ideas'!$W$2:$W$24,"COE") | H14: =COUNTIFS('All 23 Ideas'!$D$2:$D$24,$A14,'All 23 Ideas'!$W$2:$W$24,"Dental Hospital") | I14: =COUNTIFS('All 23 Ideas'!$D$2:$D$24,$A14,'All 23 Ideas'!$W$2:$W$24,"Pharmacy") | J14: =COUNTIFS('All 23 Ideas'!$D$2:$D$24,$A14,'All 23 Ideas'!$W$2:$W$24,"Procurement") | K14: dd3afcf9
A15: Total | B15: =SUM(B2:B14) | C15: =SUM(C2:C14) | D15: =SUM(D2:D14) | E15: =SUM(E2:E14) | F15: =SUM(F2:F14) | G15: =SUM(G2:G14) | H15: =SUM(H2:H14) | I15: =SUM(I2:I14) | J15: =SUM(J2:J14)

Sheet 10 Distinct Ideas
A1: Group | B1: Distinct idea | C1: Cards | D1: Master ID | E1: Master filed by | F1: Reassign to | G1: Owner to reassign to | H1: Verdict | I1: Existing MyJKKN module | J1: MyJKKN solution / suggestion
A2: A | B2: Certificate / transcript / mark sheet delays | C2: =COUNTIF('All 23 Ideas'!$S$2:$S$24,$A2) | D2: 98a8204e | E2: MOURIESWARAN A | F2: COE | G2: No COE owner on the board (coe role: Silambarasan V, COE Official, COE JKKNCAS / S. Umavathi) | H2: Approve | I2: Service Requests (/service-requests) | J2: Already live: online request, approval workflow, timeline, Bonafide / Course Completion PDF. Gaps: (1) record fulfilment - only 4 of 988 marked fulfilled; (2) notify the learner on approved / ready / rejected; (3) turnaround target + overdue filter; (4) enable certificate PDFs on all live certificate types; (5) add COE service types for transcript, duplicate / consolidated mark sheet, provisional certificate.
A3: B | B3: Dental - records delay, patient load, space, equipment (broad) | C3: =COUNTIF('All 23 Ideas'!$S$2:$S$24,$A3) | D3: dd3afcf9 | E3: VAISHNAVI P | F3: Dental Hospital | G3: Dhinesh Kumar C | H3: Send back to split | I3: None (no patient module) | J3: Too broad to build. Ask the author to re-file as one card per problem with one number each. Appointment delays are covered by c913913b and medicine expiry by 3aad071d.
A4: C | B4: Dental - token / queue system for patient crowd | C4: =COUNTIF('All 23 Ideas'!$S$2:$S$24,$A4) | D4: b5428ff8 | E4: SAVITHA K | F4: Dental Hospital | G4: Dhinesh Kumar C | H4: Merge into D and pilot together | I4: None (new build) | J4: Run as one pilot with the appointment card c913913b: slots per chair, token for walk-ins. Build a module only if the pilot reduces waiting time.
A5: D | B5: Dental - appointment reminders + follow-up tracking | C5: =COUNTIF('All 23 Ideas'!$S$2:$S$24,$A5) | D5: c913913b | E5: RUBAN R | F5: Dental Hospital | G5: Dhinesh Kumar C | H5: Approve as pilot | I5: WhatsApp integration (reminders only); no appointment module | J5: Four-week pilot in one department: shared appointment sheet, reminders through the existing MyJKKN WhatsApp integration. Measure no-shows and waiting time before and after.
A6: E | B6: Dental - medicine stock + expiry register | C6: =COUNTIF('All 23 Ideas'!$S$2:$S$24,$A6) | D6: 3aad071d | E6: SHRIYA JULIET D | F6: Dental Hospital | G6: Dhinesh Kumar C | H6: Approve | I6: Inventory (/ims) - expiry tracking | J6: Already built. Switch on expiry tracking for all dental medicine items, enter expiry at goods receipt, add a 30 / 60 / 90-day near-expiry alert. Today 0 of 56 Dental Student Store batches carry an expiry date.
A7: F | B7: Lab - dispose expired chemicals, reorganise lab | C7: =COUNTIF('All 23 Ideas'!$S$2:$S$24,$A7) | D7: c4ebb142 | E7: SAVITHA K | F7: Pharmacy | G7: Rajkumar J | H7: Approve | I7: Inventory (/ims) - expiry tracking | J7: Physical disposal is a safety action for the Pharmacy principal. In MyJKKN: track chemical expiry in Inventory. 3 JKKN Pharmacy batches are already past expiry and still in stock.
A8: G | B8: Lab - flooring, fans, lighting, ambience | C8: =COUNTIF('All 23 Ideas'!$S$2:$S$24,$A8) | D8: f255de95 | E8: SAVITHA K | F8: Pharmacy | G8: Rajkumar J | H8: Hold for details | I8: Resource Management (/resource-management) - maintenance | J8: Facilities work, not software. Log as a maintenance job once the lab is named, photographed and costed.
A9: H | B9: Pharmacy - "lab visit not permitted" + flooring | C9: =COUNTIF('All 23 Ideas'!$S$2:$S$24,$A9) | D9: 99f3eb6c | E9: SARANPRIYA R | F9: Pharmacy | G9: Rajkumar J | H9: Not pursue | I9: None | J9: Problem and fix do not match. The real finding is that entry to the lab was refused - pass to the Pharmacy owner as a Gemba access issue.
A10: I | B10: Pharmacy - barcode scan at dispensing | C10: =COUNTIF('All 23 Ideas'!$S$2:$S$24,$A10) | D10: 2db88fe5 | E10: RUBAN R | F10: Pharmacy | G10: Rajkumar J | H10: Approve as pilot | I10: Inventory (/ims) - sales / POS (no barcode field yet) | J10: Enhancement to the Inventory sales screen plus labels and scanners. Collect the baseline first: 3 months of dispensing errors and a one-week waiting-time sample.
A11: J | B11: Procurement - digital purchase request, approvals, vendor list | C11: =COUNTIF('All 23 Ideas'!$S$2:$S$24,$A11) | D11: 7793da9e | E11: RUBAN R | F11: Procurement | G11: Salini P | H11: Approve | I11: Procurement (/procurement) | J11: Already live: 38 requests, 31 RFQs, 36 quotations, 15 purchase orders. Gaps: 0 goods receipts and 0 vendor ratings. Make GRN mandatory to close a PO, start vendor ratings, enforce 3 quotations above a set amount, use reorder levels.
B12: Total cards | C12: =SUM(C2:C11)

Sheet Reassignment
A1: Reassign to | B1: Owner on the board | C1: Cards | D1: Masters to move | E1: Duplicates / not pursued to close | F1: Idea IDs
A2: COE | B2: No COE owner on the board (coe role: Silambarasan V, COE Official, COE JKKNCAS / S. Umavathi) | C2: =COUNTIF('All 23 Ideas'!$W$2:$W$24,$A2) | D2: =COUNTIFS('All 23 Ideas'!$W$2:$W$24,$A2,'All 23 Ideas'!$U$2:$U$24,"Master") | E2: =C2-D2 | F2: 98a8204e, c55831f9, de8c082c, 79dbcdab, 84cdd57b
A3: Dental Hospital | B3: Dhinesh Kumar C | C3: =COUNTIF('All 23 Ideas'!$W$2:$W$24,$A3) | D3: =COUNTIFS('All 23 Ideas'!$W$2:$W$24,$A3,'All 23 Ideas'!$U$2:$U$24,"Master") | E3: =C3-D3 | F3: dd3afcf9, 89570ea6, 3aad071d, b5428ff8, 2b02c1b6, 9c1e4cb3, fef3462a, c913913b
A4: Pharmacy | B4: Rajkumar J | C4: =COUNTIF('All 23 Ideas'!$W$2:$W$24,$A4) | D4: =COUNTIFS('All 23 Ideas'!$W$2:$W$24,$A4,'All 23 Ideas'!$U$2:$U$24,"Master") | E4: =C4-D4 | F4: c4ebb142, 04c4c414, f255de95, a301440c, 99f3eb6c, bd51d5b5, 2db88fe5, 133d6b0c
A5: Procurement | B5: Salini P | C5: =COUNTIF('All 23 Ideas'!$W$2:$W$24,$A5) | D5: =COUNTIFS('All 23 Ideas'!$W$2:$W$24,$A5,'All 23 Ideas'!$U$2:$U$24,"Master") | E5: =C5-D5 | F5: 992e5458, 7793da9e
A6: Total | C6: =SUM(C2:C5) | D6: =SUM(D2:D5) | E6: =SUM(E2:E5)
A8: Nothing has been changed on the board. Every row is a recommendation to apply by hand.
A9: Assigning a person: open the card and use "Assign people".
A10: Naming a COE owner for the area: /improvement-board/owners (needs CEO / CAO / EAO permission).
A11: Moving a card to another area has no button on the board; it needs a manual database update or a new manager action.

Sheet MyJKKN Evidence
A1: Module | B1: Measure | C1: Value | D1: Relates to group | E1: Source
A2: Service Requests | B2: Bonafide requests - total | C2: 784 | D2: A | E2: Source: MyJKKN production database, read-only query, 2026-10-09
A3: Service Requests | B3: Bonafide - marked fulfilled | C3: 3 | D3: A | E3: Source: MyJKKN production database, read-only query, 2026-10-09
A4: Service Requests | B4: Bonafide - approved, never marked fulfilled | C4: 444 | D4: A | E4: Source: MyJKKN production database, read-only query, 2026-10-09
A5: Service Requests | B5: Bonafide - approved and open more than 7 days | C5: 422 | D5: A | E5: Source: MyJKKN production database, read-only query, 2026-10-09
A6: Service Requests | B6: Bonafide - waiting for approval | C6: 102 | D6: A | E6: Source: MyJKKN production database, read-only query, 2026-10-09
A7: Service Requests | B7: Bonafide - waiting for approval more than 7 days | C7: 82 | D7: A | E7: Source: MyJKKN production database, read-only query, 2026-10-09
A8: Service Requests | B8: Bonafide - median days, submit to approve | C8: 3 | D8: A | E8: Source: MyJKKN production database, read-only query, 2026-10-09
A9: Service Requests | B9: Bonafide - 90th percentile days, submit to approve | C9: 19.6 | D9: A | E9: Source: MyJKKN production database, read-only query, 2026-10-09
A10: Service Requests | B10: Transfer Certificate requests - total | C10: 149 | D10: A | E10: Source: MyJKKN production database, read-only query, 2026-10-09
A11: Service Requests | B11: Transfer Certificate - marked fulfilled | C11: 0 | D11: A | E11: Source: MyJKKN production database, read-only query, 2026-10-09
A12: Service Requests | B12: Transfer Certificate - approved, never marked fulfilled | C12: 94 | D12: A | E12: Source: MyJKKN production database, read-only query, 2026-10-09
A13: Service Requests | B13: Transfer Certificate - approved and open more than 7 days | C13: 90 | D13: A | E13: Source: MyJKKN production database, read-only query, 2026-10-09
... A43: Resource Management | B43: Maintenance logs | C43: 90 | D43: G | E43: Source: MyJKKN production database, read-only query, 2026-10-09
B45: Certificate requests - total (Bonafide + TC + Course Completion) | C45: =C2+C10+C16
B46: Certificate requests - marked fulfilled | C46: =C3+C11+C17
B47: Certificate requests - approved, never marked fulfilled | C47: =C4+C12+C18
B48: Certificate requests - approved and open more than 7 days | C48: =C5+C13+C19
B49: Certificate requests - waiting for approval more than 7 days | C49: =C7+C15+C21
